sinabs/__init__.py
sinabs/cnnutils.py
sinabs/conversion.py
sinabs/from_torch.py
sinabs/hooks.py
sinabs/network.py
sinabs/nir.py
sinabs/synopcounter.py
sinabs/utils.py
sinabs/validate_memory_speck.py
sinabs/activation/__init__.py
sinabs/activation/quantize.py
sinabs/activation/reset_mechanism.py
sinabs/activation/spike_generation.py
sinabs/activation/surrogate_gradient_fn.py
sinabs/backend/__init__.py
sinabs/backend/dynapcnn/__init__.py
sinabs/backend/dynapcnn/chip_factory.py
sinabs/backend/dynapcnn/config_builder.py
sinabs/backend/dynapcnn/connectivity_specs.py
sinabs/backend/dynapcnn/crop2d.py
sinabs/backend/dynapcnn/discretize.py
sinabs/backend/dynapcnn/dvs_layer.py
sinabs/backend/dynapcnn/dynapcnn_layer.py
sinabs/backend/dynapcnn/dynapcnn_layer_utils.py
sinabs/backend/dynapcnn/dynapcnn_network.py
sinabs/backend/dynapcnn/dynapcnn_visualizer.py
sinabs/backend/dynapcnn/dynapcnnnetwork_module.py
sinabs/backend/dynapcnn/exceptions.py
sinabs/backend/dynapcnn/flipdims.py
sinabs/backend/dynapcnn/io.py
sinabs/backend/dynapcnn/mapping.py
sinabs/backend/dynapcnn/nir_graph_extractor.py
sinabs/backend/dynapcnn/sinabs_edges_handler.py
sinabs/backend/dynapcnn/specksim.py
sinabs/backend/dynapcnn/utils.py
sinabs/backend/dynapcnn/weight_rescaling_methods.py
sinabs/backend/dynapcnn/chips/__init__.py
sinabs/backend/dynapcnn/chips/dynapcnn.py
sinabs/backend/dynapcnn/chips/speck2e.py
sinabs/backend/dynapcnn/chips/speck2f.py
sinabs/layers/__init__.py
sinabs/layers/alif.py
sinabs/layers/channel_shift.py
sinabs/layers/crop2d.py
sinabs/layers/exp_leak.py
sinabs/layers/iaf.py
sinabs/layers/lif.py
sinabs/layers/merge.py
sinabs/layers/neuromorphic_relu.py
sinabs/layers/pool2d.py
sinabs/layers/quantize.py
sinabs/layers/reshape.py
sinabs/layers/stateful_layer.py
sinabs/layers/to_spike.py
sinabs/layers/functional/__init__.py
sinabs/layers/functional/alif.py
sinabs/layers/functional/lif.py
sinabs-3.1.2.dist-info/licenses/AUTHORS
sinabs-3.1.2.dist-info/licenses/LICENSE
sinabs-3.1.2.dist-info/METADATA
sinabs-3.1.2.dist-info/WHEEL
sinabs-3.1.2.dist-info/pbr.json
sinabs-3.1.2.dist-info/top_level.txt
sinabs-3.1.2.dist-info/RECORD
