Metadata-Version: 2.4
Name: sinabs
Version: 3.1.2
Summary: SynSense Spiking Neural Network simulator for deep neural networks (DNNs).
Author: SynSense (formerly AiCTX)
Author-email: support@synsense.ai
License: Apache 2.0
Project-URL: Source code, https://github.com/synsense/sinabs
Project-URL: Documentation, https://readthedocs.org/projects/sinabs/
Keywords: spiking neural networks,machine learning,SNN,DYNAPCNN,Speck
Classifier: Development Status :: 4 - Beta
Classifier: Environment :: Console
Classifier: Intended Audience :: Science/Research
Classifier: Intended Audience :: Developers
Classifier: License :: OSI Approved :: Apache Software License
Classifier: Programming Language :: Python :: 3
License-File: LICENSE
License-File: AUTHORS
Requires-Dist: pbr
Requires-Dist: numpy
Requires-Dist: torch>=1.8
Requires-Dist: nir<=1.0.4
Requires-Dist: nirtorch
Requires-Dist: samna>=0.33
Requires-Dist: matplotlib
Dynamic: author
Dynamic: author-email
Dynamic: classifier
Dynamic: description
Dynamic: description-content-type
Dynamic: keywords
Dynamic: license
Dynamic: license-file
Dynamic: project-url
Dynamic: requires-dist
Dynamic: summary
